Workbook
Name aporte_inicial: Simulação!$D$16
Name investim_mensal: Simulação!$D$17
Name Nper: Simulação!$D$18
Name patrimonio: Simulação!$D$20
Name rendimento: Simulação!$D$12
Name Salario: Simulação!$D$11
Name tx_rend: Simulação!$D$19

Sheet Simulação
B10: CONFIGURAÇÕES
B11: Salário | D11: 1000
B12: Rendimento da Carteira | D12: 0.006
B13: Sugestão de Investimento (30%) | D13: =Salario*30% -> 300
B15: INVESTIMENTO INICIAL
B16: Aporte Inicial | D16: 10000
B17: Valor de Investimento Mensal | D17: 560
B18: Período de Investimento (Anos) | D18: 5
B19: Taxa de Rendimento Mensal | D19: 0.0108
B20: Patrimônio Acumulado * | D20: =FV(tx_rend,Nper*12,investim_mensal,aporte_inicial)*-1 -> 65981.085
B21: Dividendos Mensais * | D21: =patrimonio*rendimento -> 395.88651
B22: * Ao final do período informado
B24: CENÁRIOS
B25: Período | C25: Valor Acumulado | D25: Dividendo
A26: 2 | B26: Valor Acumulado em 2 anos | C26: =FV(tx_rend,$A26*12,investim_mensal,aporte_inicial)*-1 -> 28190.217 | D26: =C26*rendimento -> 169.1413
A27: 5 | B27: Valor Acumulado em 5 anos | C27: =FV(tx_rend,$A27*12,investim_mensal,aporte_inicial)*-1 -> 65981.085 | D27: =C27*rendimento -> 395.88651
A28: 10 | B28: Valor Acumulado em 10 anos | C28: =FV(tx_rend,$A28*12,investim_mensal,aporte_inicial)*-1 -> 172629.72 | D28: =C28*rendimento -> 1035.7783
A29: 20 | B29: Valor Acumulado em 20 anos | C29: =FV(tx_rend,$A29*12,investim_mensal,aporte_inicial)*-1 -> 762868.73 | D29: =C29*rendimento -> 4577.2124
A30: 30 | B30: Valor Acumulado em 30 anos | C30: =FV(tx_rend,$A30*12,investim_mensal,aporte_inicial)*-1 -> 2905048.4 | D30: =C30*rendimento -> 17430.29
B32: DIVERSIFICAÇÃO DE CARTEIRA
B33: Perfil De Investidor | D33: CONSERVADOR
B34: Valor a Ser Investido Por Mês | D34: =investim_mensal -> 560
B35: Clique aqui e faça o teste para descobrir o seu perfil
B37: TIPO DE FII | C37: Percentual Sugerido | D37: Valores
B38: PAPEL | C38: =VLOOKUP($D$33&" - "&B38,Sheet1!$A$2:$D$19,4,FALSE) -> 0.3 | D38: =$D$34*C38 -> 168
B39: TIJOLO | C39: =VLOOKUP($D$33&" - "&B39,Sheet1!$A$2:$D$19,4,FALSE) -> 0.5 | D39: =$D$34*C39 -> 280
B40: HÍBRIDOS | C40: =VLOOKUP($D$33&" - "&B40,Sheet1!$A$2:$D$19,4,FALSE) -> 0.1 | D40: =$D$34*C40 -> 56
B41: FOFs | C41: =VLOOKUP($D$33&" - "&B41,Sheet1!$A$2:$D$19,4,FALSE) -> 0.1 | D41: =$D$34*C41 -> 56
B42: DESENVOLVIMENTO | C42: =VLOOKUP($D$33&" - "&B42,Sheet1!$A$2:$D$19,4,FALSE) -> 0 | D42: =$D$34*C42 -> 0
B43: HOTELARIAS | C43: =VLOOKUP($D$33&" - "&B43,Sheet1!$A$2:$D$19,4,FALSE) -> 0 | D43: =$D$34*C43 -> 0

Sheet Sheet1
A1: Chave | B1: Perfil | C1: Tipo de FII | D1: %
A2: =B2&" - "&C2 -> Conservador - PAPEL | B2: Conservador | C2: PAPEL | D2: 0.3
A3: =B3&" - "&C3 -> Conservador - TIJOLO | B3: Conservador | C3: TIJOLO | D3: 0.5
A4: =B4&" - "&C4 -> Conservador - HÍBRIDOS | B4: Conservador | C4: HÍBRIDOS | D4: 0.1
A5: =B5&" - "&C5 -> Conservador - FOFs | B5: Conservador | C5: FOFs | D5: 0.1
A6: =B6&" - "&C6 -> Conservador - DESENVOLVIMENTO | B6: Conservador | C6: DESENVOLVIMENTO | D6: 0
A7: =B7&" - "&C7 -> Conservador - HOTELARIAS | B7: Conservador | C7: HOTELARIAS | D7: 0
A8: =B8&" - "&C8 -> Moderado - PAPEL | B8: Moderado | C8: PAPEL | D8: 0.32
A9: =B9&" - "&C9 -> Moderado - TIJOLO | B9: Moderado | C9: TIJOLO | D9: 0.35
A10: =B10&" - "&C10 -> Moderado - HÍBRIDOS | B10: Moderado | C10: HÍBRIDOS | D10: 0.08
A11: =B11&" - "&C11 -> Moderado - FOFs | B11: Moderado | C11: FOFs | D11: 0.05
A12: =B12&" - "&C12 -> Moderado - DESENVOLVIMENTO | B12: Moderado | C12: DESENVOLVIMENTO | D12: 0.1
A13: =B13&" - "&C13 -> Moderado - HOTELARIAS | B13: Moderado | C13: HOTELARIAS | D13: 0.1
... A19: =B19&" - "&C19 -> Agressivo - HOTELARIAS | B19: Agressivo | C19: HOTELARIAS | D19: 0.1
